pyrchidekt/__init__.py
pyrchidekt/api.py
pyrchidekt/cards.py
pyrchidekt/categories.py
pyrchidekt/deck.py
pyrchidekt/edition.py
pyrchidekt/formats.py
pyrchidekt/mana.py
pyrchidekt/owner.py
pyrchidekt-2.2.0.dist-info/licenses/LICENSE
pyrchidekt-2.2.0.dist-info/METADATA
pyrchidekt-2.2.0.dist-info/WHEEL
pyrchidekt-2.2.0.dist-info/top_level.txt
pyrchidekt-2.2.0.dist-info/RECORD
