Metadata-Version: 2.4
Name: pyrchidekt
Version: 2.2.0
Summary: Archidekt API Wrapper for Python
Author-email: Ian Drake <linkian209@gmail.com>
License: MIT License
Keywords: archidekt,mtg,magic
Classifier: Programming Language :: Python
Requires-Python: >=3.11
License-File: LICENSE
Requires-Dist: requests
Requires-Dist: aenum
Provides-Extra: test
Requires-Dist: pytest; extra == "test"
Requires-Dist: coverage; extra == "test"
Dynamic: license-file
